LICENSE
README.md
setup.cfg
setup.py
bin/minimal-podcasts-player
minimal_podcasts_player.egg-info/PKG-INFO
minimal_podcasts_player.egg-info/SOURCES.txt
minimal_podcasts_player.egg-info/dependency_links.txt
minimal_podcasts_player.egg-info/requires.txt
minimal_podcasts_player.egg-info/top_level.txt
mpp/__init__.py
mpp/conf.py
mpp/custom.css
mpp/db.py
mpp/db.py.bck
mpp/ddbb.sql
mpp/download.py
mpp/player.py
mpp/podcasts.py
mpp/search.py
mpp/utils.py
mpp/locales/es.qm
mpp/ui/Ui_add_dialog.py
mpp/ui/Ui_config.py
mpp/ui/Ui_gui.py
mpp/ui/__init__.py
mpp/ui/custom_widgets.py
mpp/ui/images_rc.py