Metadata-Version: 2.1
Name: minimal-podcasts-player
Version: 0.4.0
Summary: Subscribe, listen and (in the future) download your favorite podcasts, quickly and easily.
Home-page: https://github.com/son-link/minimal-podcasts-player
Author: Alfonso Saavedra 'Son Link'
Author-email: sonlink.dourden@gmail.com
License: GPL 3.0
Download-URL: https://github.com/son-link/minimal-podcasts-player/archive/0.3.1.tar.gz
Keywords: podcasts,audio,stream
Platform: UNKNOWN
Classifier: Development Status :: 4 - Beta
Classifier: Environment :: X11 Applications :: Qt
Classifier: Topic :: Multimedia :: Sound/Audio
Classifier: Topic :: Multimedia :: Sound/Audio :: Players
Classifier: License :: OSI Approved :: GNU General Public License v3 or later (GPLv3+)
Classifier: Programming Language :: Python :: 3
Classifier: Programming Language :: Python :: 3.4
Classifier: Programming Language :: Python :: 3.5
Classifier: Programming Language :: Python :: 3.6
Classifier: Programming Language :: Python :: 3.7
Classifier: Programming Language :: Python :: 3.8
Classifier: Programming Language :: Python :: 3.9
Classifier: Intended Audience :: End Users/Desktop
Classifier: Operating System :: OS Independent
License-File: LICENSE
